sharepoint_online/__init__.py
sharepoint_online/auth.py
sharepoint_online/list.py
sharepoint_online/sharepoint.py
sharepoint_online_python-0.0.10.dist-info/LICENSE
sharepoint_online_python-0.0.10.dist-info/METADATA
sharepoint_online_python-0.0.10.dist-info/WHEEL
sharepoint_online_python-0.0.10.dist-info/top_level.txt
sharepoint_online_python-0.0.10.dist-info/RECORD
